{
  "id": "enrique-zamudio",
  "name": "Enrique Zamudio",
  "photoUrl": "/img/speakers/enrique-zamudio.jpg",
  "title": "Ingeniero Principal",
  "shortBio": "Enrique Zamudio es programador profesional desde 1994, con sede en Ciudad de México. Se ha especializado en el desarrollo del lado del servidor con Java desde el año 2000, centrándose en aplicaciones backend, como conmutadores transaccionales para comercio electrónico y plataformas de pago. Es autor de los proyectos de código abierto jAlarms, j8583 y ScalaSQL. Enrique se unió al equipo central de desarrollo de Ceylon Language en enero de 2012, donde ha contribuido al módulo de lenguaje, el IDE web y el compilador JVM, y es el desarrollador principal del compilador Ceylon-to-JavaScript.",
  "countryFlag": "flag-icon-mx",
  "bio": "",
  "tags": [],
  "socials": [
    {
      "icon": "twitter",
      "name": "Twitter",
      "link": "https://twitter.com/chochosmx"
    },
    {
      "icon": "link",
      "name": "link",
      "link": "http://www.javamexico.org/blogs/ezamudio"
    }
  ]
}