{
    "id": "yuri-santana",
    "name": "Yuri Santana",
    "photoUrl": "/archive/jconf2023/images/speakers/yuri-santana.jpg",
	"title": "DevRel",
    "shortBio": "",
    "countryFlag": "flag-icon-do",  
    "bio": "Yuri es una dominicana que cambió de leyes a programación durante la pandemia, actualmente trabaja como DevRel y crea contenido para ayudar a esas personas que están empezando con su camino en tech (code newbies) y aquellos que ya están más experimentados. Ella forma parte de varias comunidades de DevRels y de programación en la que cabe destacar una participación activa en DevRelX y ha impartido charlas para la comunidad de GitHub en español. Siempre está aprendiendo cosas nuevas y conectando con la comunidad.",
    "socials": [
        {
            "icon": "link",
            "name": "Linktr.ee",
            "link": "https://linktr.ee/YuriCodesBot"
        }
    ]
}